cli/__init__.py
cli/deployment.py
cli/main.py
cli/service.py
cli/utils.py
oblv/__init__.py
oblv/auth.py
oblv/client.py
oblv/config.py
oblv/exceptions.py
oblv/oblv_client.py
oblv/py.typed
oblv/types.py
oblv/utils.py
oblv/api/__init__.py
oblv/api/account/__init__.py
oblv/api/account/get_user_accounts_account_get.py
oblv/api/auth/__init__.py
oblv/api/auth/authenticate_key_login_apikey_post.py
oblv/api/auth/logout_session_logout_delete.py
oblv/api/deployment/__init__.py
oblv/api/deployment/create_new_deployment_deployment_post.py
oblv/api/deployment/delete_deployment_deployment_delete.py
oblv/api/deployment/generate_build_args_deployment_arguments_get.py
oblv/api/deployment/get_available_deployments_deployment_available_get.py
oblv/api/deployment/get_deployment_info_deployment_get.py
oblv/api/deployment/get_deployment_roles_deployment_roles_get.py
oblv/api/deployment/get_supported_regions_deployment_supported_regions_get.py
oblv/api/deployment/get_user_owned_deployments_deployment_owned_get.py
oblv/api/notification/__init__.py
oblv/api/notification/get_all_notifications_notification_get.py
oblv/api/notification/get_notification_details_notification_notification_id_get.py
oblv/api/notification/mark_all_notification_read_notification_delete.py
oblv/api/notification/mark_notification_read_notification_notification_id_delete.py
oblv/api/repo/__init__.py
oblv/api/repo/get_all_repos_repo_linked_get.py
oblv/api/repo/get_repo_from_vcs_repo_get.py
oblv/api/repo/get_repo_refs_repo_refs_get.py
oblv/api/repo/get_repo_repo_repo_id_get.py
oblv/api/repo/get_repo_repo_repo_owner_repo_name_get.py
oblv/api/repo/search_repo_from_vcs_repo_search_get.py
oblv/api/service/__init__.py
oblv/api/service/add_repo_service_repo_service_post.py
oblv/api/service/delete_repo_services_repo_service_delete.py
oblv/api/service/get_repo_service_yaml_form_content_repo_service_yaml_get.py
oblv/api/service/get_repo_services_repo_service_get.py
oblv/api/service/get_user_services_service_get.py
PyOblv-0.2.0.dist-info/LICENSE
PyOblv-0.2.0.dist-info/METADATA
PyOblv-0.2.0.dist-info/WHEEL
PyOblv-0.2.0.dist-info/entry_points.txt
PyOblv-0.2.0.dist-info/top_level.txt
PyOblv-0.2.0.dist-info/RECORD
