Metadata-Version: 2.1
Name: PyOblv
Version: 0.2.0
Summary: A client library for accessing Oblivious OpenAPIs
Home-page: https://github.com/ObliviousAI/PyOblv
Author: Oblivious
Author-email: hello@oblivious.ai
License: Apache License 2.0
Project-URL: Documentation, https://github.com/ObliviousAI/PyOblv/tree/master/README.md
Project-URL: Source, https://github.com/ObliviousAI/PyOblv
Project-URL: Tracker, https://github.com/ObliviousAI/PyOblv/issues
Keywords: Oblivious python package
Classifier: Development Status :: 3 - Alpha
Classifier: Intended Audience :: Developers
Classifier: License :: OSI Approved :: Apache Software License
Classifier: Programming Language :: Python :: 3.7
Classifier: Programming Language :: Python :: 3.8
Classifier: Programming Language :: Python :: 3.9
Requires-Python: >=3.7, <4
License-File: LICENSE
Requires-Dist: httpx (<0.24.0,>=0.15.0)
Requires-Dist: attrs (>=21.3.0)
Requires-Dist: python-dateutil (<3,>=2.8.0)
Requires-Dist: jsonschema (>=4.1.1)
Requires-Dist: typer (>=0.7.0)
Requires-Dist: rich (>=11.2.0)
Requires-Dist: requests
